barmuscomp/__init__.py
barmuscomp/ae.py
barmuscomp/ae_ntd.py
barmuscomp/ae_utils.py
barmuscomp/lra.py
barmuscomp/model/__init__.py
barmuscomp/model/common_plot.py
barmuscomp/model/early_stopping.py
barmuscomp/model/errors.py
barmuscomp/model/factorisation_to_signal.py
barmuscomp/model/plot_comparison_ae_ntd.py
barmuscomp/model/signal_to_spectrogram.py
barmuscomp/model/spectrogram_to_signal.py
barmuscomp/scripts/__init__.py
barmuscomp/scripts/default_path.py
barmuscomp/scripts/overall_scripts.py
barmuscomp-0.1.6.dist-info/AUTHORS
barmuscomp-0.1.6.dist-info/LICENSE.md
barmuscomp-0.1.6.dist-info/METADATA
barmuscomp-0.1.6.dist-info/WHEEL
barmuscomp-0.1.6.dist-info/top_level.txt
barmuscomp-0.1.6.dist-info/RECORD
