Metadata-Version: 2.1
Name: barmuscomp
Version: 0.1.6
Summary: Package for barwise compression applied on musical segmentation.
Home-page: https://gitlab.imt-atlantique.fr/a23marmo/barmuscomp
Author: Marmoret Axel
Author-email: axel.marmoret@imt-atlantique.fr
License: BSD
Platform: UNKNOWN
Classifier: License :: OSI Approved :: BSD License
Classifier: Programming Language :: Python
Classifier: Development Status :: 3 - Alpha
Classifier: Intended Audience :: Developers
Classifier: Intended Audience :: Science/Research
Classifier: Topic :: Multimedia :: Sound/Audio :: Analysis
Classifier: Programming Language :: Python :: 3.8
License-File: LICENSE.md
License-File: AUTHORS
Requires-Dist: as-seg
Requires-Dist: base-audio
Requires-Dist: librosa (>=0.10)
Requires-Dist: madmom (>=0.16.1)
Requires-Dist: matplotlib
Requires-Dist: mir-eval (>=0.6)
Requires-Dist: mirdata (>=0.3.3)
Requires-Dist: nn-fac (>=0.3.2)
Requires-Dist: numpy (>=1.18.2)
Requires-Dist: pandas
Requires-Dist: scikit-learn
Requires-Dist: scipy (>=1.4.1)
Requires-Dist: smart-open
Requires-Dist: tensorly (>=0.5.1)
Requires-Dist: torch (>=1.8.0)
